README.md
setup.py
pulumi_prowlarr/__init__.py
pulumi_prowlarr/_utilities.py
pulumi_prowlarr/provider.py
pulumi_prowlarr/pulumi-plugin.json
pulumi_prowlarr/py.typed
pulumi_prowlarr.egg-info/PKG-INFO
pulumi_prowlarr.egg-info/SOURCES.txt
pulumi_prowlarr.egg-info/dependency_links.txt
pulumi_prowlarr.egg-info/not-zip-safe
pulumi_prowlarr.egg-info/requires.txt
pulumi_prowlarr.egg-info/top_level.txt
pulumi_prowlarr/applications/__init__.py
pulumi_prowlarr/applications/application.py
pulumi_prowlarr/applications/get_application.py
pulumi_prowlarr/applications/get_applications.py
pulumi_prowlarr/applications/get_sync_profile.py
pulumi_prowlarr/applications/get_sync_profiles.py
pulumi_prowlarr/applications/lazy_librarian.py
pulumi_prowlarr/applications/lidarr.py
pulumi_prowlarr/applications/mylar.py
pulumi_prowlarr/applications/outputs.py
pulumi_prowlarr/applications/radarr.py
pulumi_prowlarr/applications/readarr.py
pulumi_prowlarr/applications/sonarr.py
pulumi_prowlarr/applications/sync_profile.py
pulumi_prowlarr/applications/whisparr.py
pulumi_prowlarr/config/__init__.py
pulumi_prowlarr/config/vars.py
pulumi_prowlarr/downloadclients/__init__.py
pulumi_prowlarr/downloadclients/_inputs.py
pulumi_prowlarr/downloadclients/aria2.py
pulumi_prowlarr/downloadclients/deluge.py
pulumi_prowlarr/downloadclients/download_client.py
pulumi_prowlarr/downloadclients/flood.py
pulumi_prowlarr/downloadclients/freebox.py
pulumi_prowlarr/downloadclients/get_download_client.py
pulumi_prowlarr/downloadclients/get_download_clients.py
pulumi_prowlarr/downloadclients/hadouken.py
pulumi_prowlarr/downloadclients/nzbget.py
pulumi_prowlarr/downloadclients/nzbvortex.py
pulumi_prowlarr/downloadclients/outputs.py
pulumi_prowlarr/downloadclients/pneumatic.py
pulumi_prowlarr/downloadclients/qbittorrent.py
pulumi_prowlarr/downloadclients/rtorrent.py
pulumi_prowlarr/downloadclients/sabnzbd.py
pulumi_prowlarr/downloadclients/torrent_blackhole.py
pulumi_prowlarr/downloadclients/torrent_download_station.py
pulumi_prowlarr/downloadclients/transmission.py
pulumi_prowlarr/downloadclients/usenet_blackhole.py
pulumi_prowlarr/downloadclients/usenet_download_station.py
pulumi_prowlarr/downloadclients/utorrent.py
