Metadata-Version: 2.1
Name: pulumi-prowlarr
Version: 3.0.0a2
Summary: A Pulumi package for creating and managing Prowlarr resources
Home-page: https://github.com/MaienM/pulumi-prowlarr
License: Apache-2.0
Project-URL: Repository, https://github.com/MaienM/pulumi-prowlarr
Keywords: pulumi prowlarr category/utility
Requires-Python: >=3.7
